{"concepts": [{"id": 10, "sequence": 5, "description": "Absolute Value", "children": [{"id": 124, "description": "Rounding"}, {"id": 19, "description": "Estimation"}], "dimensions": [2, 2], "terminal": 0, "probability_true": [0.98, 0.98, 0.12, 0.12], "probability_false": [0.02, 0.02, 0.88, 0.88], "proficiency": 0.2232517814660376, "degreeCarefull": 1, "gender": "Female", "known": 0.2232517814660376, "learnt": 0, "age": 14, "classID": 1}, {"id": 11, "sequence": 5, "description": "Addition and Subtraction Fractions", "children": [{"id": 124, "description": "Rounding"}, {"id": 19, "description": "Estimation"}], "dimensions": [2, 2], "terminal": 0, "probability_true": [0.98, 0.98, 0.12, 0.12], "probability_false": [0.02, 0.02, 0.88, 0.88], "proficiency": 0.17394567271128505, "degreeCarefull": 1, "gender": "Female", "known": 0.17394567271128505, "learnt": 0, "age": 14, "classID": 1}, {"id": 12, "sequence": 1, "description": "Addition and Subtraction Integers", "children": [{"id": 14, "description": "Counting Methods"}], "dimensions": [2], "terminal": 0, "probability_true": [0.98, 0.12], "probability_false": [0.02, 0.88], "proficiency": 0.23905922758702097, "degreeCarefull": 1, "gender": "Female", "known": 0.23905922758702097, "learnt": 0, "age": 14, "classID": 1}, {"id": 13, "sequence": 2, "description": "Conversion of Fraction Decimals Percents", "children": [{"id": 122, "description": "Percent Of"}], "dimensions": [2], "terminal": 0, "probability_true": [0.98, 0.12], "probability_false": [0.02, 0.88], "proficiency": 0.2823878079710153, "degreeCarefull": 1, "gender": "Female", "known": 0.2823878079710153, "learnt": 0, "age": 14, "classID": 1}, {"id": 14, "sequence": 0, "description": "Counting Methods", "children": [], "dimensions": [2, 2], "terminal": 1, "probability_true": [0.33], "probability_false": [0.67], "proficiency": 0.3161446674687365, "degreeCarefull": 0, "gender": "Female", "known": 0.3161446674687365, "learnt": 0, "age": 14, "classID": 1}, {"id": 15, "sequence": 0, "description": "Definition Pi", "children": [], "dimensions": [2, 2], "terminal": 1, "probability_true": [0.33], "probability_false": [0.67], "proficiency": 0.17923731410502733, "degreeCarefull": 1, "gender": "Female", "known": 0.17923731410502733, "learnt": 0, "age": 14, "classID": 1}, {"id": 16, "sequence": 0, "description": "Divisibility Rules", "children": [], "dimensions": [2, 2], "terminal": 1, "probability_true": [0.33], "probability_false": [0.67], "proficiency": 0.19902603710393096, "degreeCarefull": 1, "gender": "Female", "known": 0.19902603710393096, "learnt": 0, "age": 14, "classID": 1}, {"id": 17, "sequence": 1, "description": "Division Fractions", "children": [{"id": 16, "description": "Divisibility Rules"}], "dimensions": [2], "terminal": 0, "probability_true": [0.98, 0.12], "probability_false": [0.02, 0.88], "proficiency": 0.24923757500542354, "degreeCarefull": 0, "gender": "Female", "known": 0.24923757500542354, "learnt": 0, "age": 14, "classID": 1}, {"id": 18, "sequence": 0, "description": "English and Metric Terminology", "children": [], "dimensions": [2, 2], "terminal": 1, "probability_true": [0.33], "probability_false": [0.67], "proficiency": 0.2507516790438855, "degreeCarefull": 1, "gender": "Female", "known": 0.2507516790438855, "learnt": 0, "age": 14, "classID": 1}, {"id": 19, "sequence": 4, "description": "Estimation", "children": [{"id": 124, "description": "Rounding"}], "dimensions": [2], "terminal": 0, "probability_true": [0.98, 0.12], "probability_false": [0.02, 0.88], "proficiency": 0.2800090690175594, "degreeCarefull": 1, "gender": "Female", "known": 0.2800090690175594, "learnt": 0, "age": 14, "classID": 1}, {"id": 110, "sequence": 0, "description": "Finding Percents", "children": [], "dimensions": [2, 2], "terminal": 1, "probability_true": [0.33], "probability_false": [0.67], "proficiency": 0.24544191726978867, "degreeCarefull": 0, "gender": "Female", "known": 0.24544191726978867, "learnt": 0, "age": 14, "classID": 1}, {"id": 111, "sequence": 0, "description": "Finding Ratios", "children": [{"id": 19, "description": "Estimation"}], "dimensions": [2], "terminal": 0, "probability_true": [0.98, 0.12], "probability_false": [0.02, 0.88], "proficiency": 0.21560146082161902, "degreeCarefull": 0, "gender": "Female", "known": 0.21560146082161902, "learnt": 0, "age": 14, "classID": 1}, {"id": 112, "sequence": 3, "description": "Greatest Common Factor", "children": [{"id": 16, "description": "Divisibility Rules"}, {"id": 114, "description": "Multiplication and Division Integers"}], "dimensions": [2, 2], "terminal": 0, "probability_true": [0.98, 0.98, 0.12, 0.12], "probability_false": [0.02, 0.02, 0.88, 0.88], "proficiency": 0.27141905902942076, "degreeCarefull": 0, "gender": "Female", "known": 0.27141905902942076, "learnt": 0, "age": 14, "classID": 1}, {"id": 113, "sequence": 3, "description": "Least Common Multiple", "children": [{"id": 16, "description": "Divisibility Rules"}, {"id": 114, "description": "Multiplication and Division Integers"}], "dimensions": [2, 2], "terminal": 0, "probability_true": [0.98, 0.98, 0.12, 0.12], "probability_false": [0.02, 0.02, 0.88, 0.88], "proficiency": 0.25458865602213787, "degreeCarefull": 1, "gender": "Female", "known": 0.25458865602213787, "learnt": 0, "age": 14, "classID": 1}, {"id": 114, "sequence": 1, "description": "Multiplication and Division Integers", "children": [{"id": 16, "description": "Divisibility Rules"}], "dimensions": [2], "terminal": 0, "probability_true": [0.98, 0.12], "probability_false": [0.02, 0.88], "proficiency": 0.28570199588194395, "degreeCarefull": 1, "gender": "Female", "known": 0.6053974762186158, "learnt": 1, "age": 14, "classID": 1}, {"id": 115, "sequence": 3, "description": "Multiplication Fractions", "children": [{"id": 16, "description": "Divisibility Rules"}, {"id": 114, "description": "Multiplication and Division Integers"}], "dimensions": [2, 2], "terminal": 0, "probability_true": [0.98, 0.98, 0.12, 0.12], "probability_false": [0.02, 0.02, 0.88, 0.88], "proficiency": 0.22150342702163592, "degreeCarefull": 1, "gender": "Female", "known": 0.22150342702163592, "learnt": 0, "age": 14, "classID": 1}, {"id": 116, "sequence": 0, "description": "Number Line", "children": [], "dimensions": [2, 2], "terminal": 1, "probability_true": [0.33], "probability_false": [0.67], "proficiency": 0.23128232338496715, "degreeCarefull": 1, "gender": "Female", "known": 0.23128232338496715, "learnt": 0, "age": 14, "classID": 1}, {"id": 117, "sequence": 0, "description": "Order of Operations +,-,/,* () positive reals", "children": [], "dimensions": [2, 2], "terminal": 1, "probability_true": [0.33], "probability_false": [0.67], "proficiency": 0.2125449715932571, "degreeCarefull": 1, "gender": "Female", "known": 0.2125449715932571, "learnt": 0, "age": 14, "classID": 1}, {"id": 118, "sequence": 1, "description": "Order of Operations All", "children": [{"id": 117, "description": "Order of Operations +,-,/,* () positive reals"}], "dimensions": [2], "terminal": 0, "probability_true": [0.98, 0.12], "probability_false": [0.02, 0.88], "proficiency": 0.2052413356381967, "degreeCarefull": 0, "gender": "Female", "known": 0.2052413356381967, "learnt": 0, "age": 14, "classID": 1}, {"id": 119, "sequence": 1, "description": "Ordering Positive Decimals", "children": [{"id": 116, "description": "Number Line"}], "dimensions": [2], "terminal": 0, "probability_true": [0.98, 0.12], "probability_false": [0.02, 0.88], "proficiency": 0.2245116876279757, "degreeCarefull": 0, "gender": "Female", "known": 0.2245116876279757, "learnt": 0, "age": 14, "classID": 1}, {"id": 120, "sequence": 0, "description": "Pattern Finding ", "children": [], "dimensions": [2, 2], "terminal": 1, "probability_true": [0.33], "probability_false": [0.67], "proficiency": 0.20543461077404895, "degreeCarefull": 1, "gender": "Female", "known": 0.20543461077404895, "learnt": 0, "age": 14, "classID": 1}, {"id": 121, "sequence": 2, "description": "Percent Discount", "children": [{"id": 122, "description": "Percent Of"}], "dimensions": [2], "terminal": 0, "probability_true": [0.98, 0.12], "probability_false": [0.02, 0.88], "proficiency": 0.24475565895462323, "degreeCarefull": 0, "gender": "Female", "known": 0.24475565895462323, "learnt": 0, "age": 14, "classID": 1}, {"id": 122, "sequence": 1, "description": "Percent Of 2", "children": [{"id": 16, "description": "Divisibility Rules"}, {"id": 110, "description": "Finding Percents"}], "dimensions": [2, 2], "terminal": 0, "probability_true": [0.98, 0.98, 0.12, 0.12], "probability_false": [0.02, 0.02, 0.88, 0.88], "proficiency": 0.25265220799150284, "degreeCarefull": 0, "gender": "Female", "known": 0.583993160270772, "learnt": 1, "age": 14, "classID": 1}, {"id": 123, "sequence": 0, "description": "Prime Factor", "children": [{"id": 112, "description": "Greatest Common Factor"}], "dimensions": [2], "terminal": 0, "probability_true": [0.98, 0.12], "probability_false": [0.02, 0.88], "proficiency": 0.23939607300570404, "degreeCarefull": 1, "gender": "Female", "known": 0.23939607300570404, "learnt": 0, "age": 14, "classID": 1}, {"id": 124, "sequence": 3, "description": "Rounding", "children": [{"id": 16, "description": "Divisibility Rules"}, {"id": 114, "description": "Multiplication and Division Integers"}], "dimensions": [2, 2], "terminal": 0, "probability_true": [0.98, 0.98, 0.12, 0.12], "probability_false": [0.02, 0.02, 0.88, 0.88], "proficiency": 0.3394105481512657, "degreeCarefull": 1, "gender": "Female", "known": 0.3394105481512657, "learnt": 0, "age": 14, "classID": 1}, {"id": 125, "sequence": 0, "description": "Scientific Notation", "children": [], "dimensions": [2, 2], "terminal": 1, "probability_true": [0.33], "probability_false": [0.67], "proficiency": 0.2120026991952784, "degreeCarefull": 0, "gender": "Female", "known": 0.2120026991952784, "learnt": 0, "age": 14, "classID": 1}, {"id": 126, "sequence": 1, "description": "Unit Conversion Standard to Metric", "children": [{"id": 18, "description": "English and Metric Terminology"}], "dimensions": [2], "terminal": 0, "probability_true": [0.98, 0.12], "probability_false": [0.02, 0.88], "proficiency": 0.22779711305457473, "degreeCarefull": 0, "gender": "Female", "known": 0.22779711305457473, "learnt": 0, "age": 14, "classID": 1}, {"id": 127, "sequence": 2, "description": "Unit Conversion Within a System", "children": [{"id": 18, "description": "English and Metric Terminology"}, {"id": 125, "description": "Scientific Notation"}], "dimensions": [2, 2], "terminal": 0, "probability_true": [0.98, 0.98, 0.12, 0.12], "probability_false": [0.02, 0.02, 0.88, 0.88], "proficiency": 0.22265264702998708, "degreeCarefull": 0, "gender": "Female", "known": 0.22265264702998708, "learnt": 0, "age": 14, "classID": 1}, {"id": 20, "sequence": 6, "description": "Angles - Obtuse, Acute, and Right", "children": [], "dimensions": [2, 2], "terminal": 1, "probability_true": [0.33], "probability_false": [0.67], "proficiency": 0.804581286421313, "degreeCarefull": 1, "gender": "Female", "known": 0.804581286421313, "learnt": 0, "age": 14, "classID": 1}, {"id": 21, "sequence": 7, "description": "Angles on Parallel Lines Cut by a Transversal", "children": [{"id": 20, "description": "Angles - Obtuse, Acute, and Right"}], "dimensions": [2], "terminal": 0, "probability_true": [0.98, 0.12], "probability_false": [0.02, 0.88], "proficiency": 0.17095988137743023, "degreeCarefull": 0, "gender": "Female", "known": 0.17095988137743023, "learnt": 0, "age": 14, "classID": 1}, {"id": 22, "sequence": 6, "description": "Area Concept", "children": [], "dimensions": [2, 2], "terminal": 1, "probability_true": [0.33], "probability_false": [0.67], "proficiency": 0.16812270535084323, "degreeCarefull": 1, "gender": "Female", "known": 0.16812270535084323, "learnt": 0, "age": 14, "classID": 1}, {"id": 23, "sequence": 8, "description": "Area Circle", "children": [{"id": 22, "description": "Area Concept"}], "dimensions": [2], "terminal": 0, "probability_true": [0.98, 0.12], "probability_false": [0.02, 0.88], "proficiency": 0.21635766051016792, "degreeCarefull": 1, "gender": "Female", "known": 0.21635766051016792, "learnt": 0, "age": 14, "classID": 1}, {"id": 24, "sequence": 7, "description": "Area Irregular Figure", "children": [{"id": 22, "description": "Area Concept"}], "dimensions": [2], "terminal": 0, "probability_true": [0.98, 0.12], "probability_false": [0.02, 0.88], "proficiency": 0.23719767357421517, "degreeCarefull": 1, "gender": "Female", "known": 0.23719767357421517, "learnt": 0, "age": 14, "classID": 1}, {"id": 25, "sequence": 7, "description": "Area Parallelogram", "children": [{"id": 22, "description": "Area Concept"}], "dimensions": [2], "terminal": 0, "probability_true": [0.98, 0.12], "probability_false": [0.02, 0.88], "proficiency": 0.23331405065945932, "degreeCarefull": 0, "gender": "Female", "known": 0.23331405065945932, "learnt": 0, "age": 14, "classID": 1}, {"id": 26, "sequence": 7, "description": "Area Rectangle", "children": [{"id": 22, "description": "Area Concept"}], "dimensions": [2], "terminal": 0, "probability_true": [0.98, 0.12], "probability_false": [0.02, 0.88], "proficiency": 0.31558542808809714, "degreeCarefull": 0, "gender": "Female", "known": 0.31558542808809714, "learnt": 0, "age": 14, "classID": 1}, {"id": 27, "sequence": 7, "description": "Area Trapezoid", "children": [{"id": 22, "description": "Area Concept"}], "dimensions": [2], "terminal": 0, "probability_true": [0.98, 0.12], "probability_false": [0.02, 0.88], "proficiency": 0.24537811690236894, "degreeCarefull": 0, "gender": "Female", "known": 0.24537811690236894, "learnt": 0, "age": 14, "classID": 1}, {"id": 28, "sequence": 7, "description": "Area Triangle", "children": [{"id": 22, "description": "Area Concept"}], "dimensions": [2], "terminal": 0, "probability_true": [0.98, 0.12], "probability_false": [0.02, 0.88], "proficiency": 0.2325892102181397, "degreeCarefull": 0, "gender": "Female", "known": 0.2325892102181397, "learnt": 0, "age": 14, "classID": 1}, {"id": 29, "sequence": 6, "description": "Calculations with Similar Figures", "children": [{"id": 214, "description": "Congruence"}], "dimensions": [2], "terminal": 0, "probability_true": [0.98, 0.12], "probability_false": [0.02, 0.88], "proficiency": 0.24085885980300326, "degreeCarefull": 1, "gender": "Female", "known": 0.24085885980300326, "learnt": 0, "age": 14, "classID": 1}, {"id": 210, "sequence": 7, "description": "Circle Concep", "children": [{"id": 15, "description": "Definition Pi"}], "dimensions": [2], "terminal": 0, "probability_true": [0.98, 0.12], "probability_false": [0.02, 0.88], "proficiency": 0.1922220436463311, "degreeCarefull": 1, "gender": "Female", "known": 0.1922220436463311, "learnt": 0, "age": 14, "classID": 1}, {"id": 211, "sequence": 6, "description": "Circumference", "children": [], "dimensions": [2, 2], "terminal": 1, "probability_true": [0.33], "probability_false": [0.67], "proficiency": 0.22258175065203725, "degreeCarefull": 0, "gender": "Female", "known": 0.22258175065203725, "learnt": 0, "age": 14, "classID": 1}, {"id": 212, "sequence": 6, "description": "Complementary and Supplementary Angles", "children": [{"id": 20, "description": "Angles - Obtuse, Acute, and Right"}], "dimensions": [2], "terminal": 0, "probability_true": [0.98, 0.12], "probability_false": [0.02, 0.88], "proficiency": 0.2110449209879335, "degreeCarefull": 1, "gender": "Female", "known": 0.2110449209879335, "learnt": 0, "age": 14, "classID": 1}, {"id": 213, "sequence": 6, "description": "Concept Volume", "children": [], "dimensions": [2, 2], "terminal": 1, "probability_true": [0.33], "probability_false": [0.67], "proficiency": 0.23004725275781382, "degreeCarefull": 1, "gender": "Female", "known": 0.23004725275781382, "learnt": 0, "age": 14, "classID": 1}, {"id": 214, "sequence": 6, "description": "Congruence", "children": [], "dimensions": [2, 2], "terminal": 1, "probability_true": [0.33], "probability_false": [0.67], "proficiency": 0.20786623233530058, "degreeCarefull": 1, "gender": "Female", "known": 0.20786623233530058, "learnt": 0, "age": 14, "classID": 1}, {"id": 215, "sequence": 6, "description": "Effect of Changing Dimensions of a Shape Proportionally", "children": [{"id": 214, "description": "Congruence"}, {"id": 227, "description": "Proportion"}], "dimensions": [2, 2], "terminal": 0, "probability_true": [0.98, 0.98, 0.12, 0.12], "probability_false": [0.02, 0.02, 0.88, 0.88], "proficiency": 0.24907545550555268, "degreeCarefull": 1, "gender": "Female", "known": 0.24907545550555268, "learnt": 0, "age": 14, "classID": 1}, {"id": 216, "sequence": 6, "description": "Interior Angles Figures with More than 3 Sides", "children": [{"id": 20, "description": "Angles - Obtuse, Acute, and Right"}], "dimensions": [2], "terminal": 0, "probability_true": [0.98, 0.12], "probability_false": [0.02, 0.88], "proficiency": 0.24771953192968968, "degreeCarefull": 0, "gender": "Female", "known": 0.24771953192968968, "learnt": 0, "age": 14, "classID": 1}, {"id": 217, "sequence": 7, "description": "Interior Angles Triangle", "children": [{"id": 226, "description": "Properties and Classification Triangles"}], "dimensions": [2], "terminal": 0, "probability_true": [0.98, 0.12], "probability_false": [0.02, 0.88], "proficiency": 0.16420328849679955, "degreeCarefull": 1, "gender": "Female", "known": 0.16420328849679955, "learnt": 0, "age": 14, "classID": 1}, {"id": 218, "sequence": 9, "description": "Volume Sphere", "children": [{"id": 213, "description": "Concept Volume"}], "dimensions": [2], "terminal": 0, "probability_true": [0.98, 0.12], "probability_false": [0.02, 0.88], "proficiency": 0.18507598637116868, "degreeCarefull": 0, "gender": "Female", "known": 0.18507598637116868, "learnt": 0, "age": 14, "classID": 1}, {"id": 219, "sequence": 7, "description": "Nets of 3D Objects", "children": [{"id": 22, "description": "Area Concept"}], "dimensions": [2], "terminal": 0, "probability_true": [0.98, 0.12], "probability_false": [0.02, 0.88], "proficiency": 0.22084326133369908, "degreeCarefull": 1, "gender": "Female", "known": 0.22084326133369908, "learnt": 0, "age": 14, "classID": 1}, {"id": 220, "sequence": 6, "description": "Parallel and Perpendicular Lines", "children": [{"id": 20, "description": "Angles - Obtuse, Acute, and Right"}], "dimensions": [2], "terminal": 0, "probability_true": [0.98, 0.12], "probability_false": [0.02, 0.88], "proficiency": 0.18121480078358695, "degreeCarefull": 0, "gender": "Female", "known": 0.18121480078358695, "learnt": 0, "age": 14, "classID": 1}, {"id": 221, "sequence": 8, "description": "Perimeter of a Polygon", "children": [{"id": 211, "description": "Circumference"}], "dimensions": [2], "terminal": 0, "probability_true": [0.98, 0.12], "probability_false": [0.02, 0.88], "proficiency": 0.09114292849900936, "degreeCarefull": 1, "gender": "Female", "known": 0.09114292849900936, "learnt": 0, "age": 14, "classID": 1}, {"id": 222, "sequence": 6, "description": "Properties and Classification Polygons with 5 or more sides", "children": [{"id": 221, "description": "Perimeter of a Polygon"}], "dimensions": [2], "terminal": 0, "probability_true": [0.98, 0.12], "probability_false": [0.02, 0.88], "proficiency": 0.24573996707877982, "degreeCarefull": 0, "gender": "Female", "known": 0.24573996707877982, "learnt": 0, "age": 14, "classID": 1}, {"id": 223, "sequence": 6, "description": "Properties and Classification Prism", "children": [], "dimensions": [2, 2], "terminal": 1, "probability_true": [0.33], "probability_false": [0.67], "proficiency": 0.23933368186868254, "degreeCarefull": 1, "gender": "Female", "known": 0.23933368186868254, "learnt": 0, "age": 14, "classID": 1}, {"id": 224, "sequence": 6, "description": "Properties and Classification Quadrilaterals", "children": [{"id": 220, "description": "Parallel and Perpendicular Lines"}], "dimensions": [2], "terminal": 0, "probability_true": [0.98, 0.12], "probability_false": [0.02, 0.88], "proficiency": 0.14866387863162503, "degreeCarefull": 1, "gender": "Female", "known": 0.14866387863162503, "learnt": 0, "age": 14, "classID": 1}, {"id": 225, "sequence": 6, "description": "Properties and Classification Rectangular Prisms", "children": [], "dimensions": [2, 2], "terminal": 1, "probability_true": [0.33], "probability_false": [0.67], "proficiency": 0.28149333852178987, "degreeCarefull": 1, "gender": "Female", "known": 0.28149333852178987, "learnt": 0, "age": 14, "classID": 1}, {"id": 226, "sequence": 6, "description": "Properties and Classification Triangles", "children": [], "dimensions": [2, 2], "terminal": 1, "probability_true": [0.33], "probability_false": [0.67], "proficiency": 0.751372361573148, "degreeCarefull": 1, "gender": "Female", "known": 0.751372361573148, "learnt": 0, "age": 14, "classID": 1}, {"id": 227, "sequence": 6, "description": "Proportion", "children": [{"id": 229, "description": "Scale Factor"}], "dimensions": [2], "terminal": 0, "probability_true": [0.98, 0.12], "probability_false": [0.02, 0.88], "proficiency": 0.28998746235997763, "degreeCarefull": 0, "gender": "Female", "known": 0.28998746235997763, "learnt": 0, "age": 14, "classID": 1}, {"id": 228, "sequence": 6, "description": "Pythagorean Theorem", "children": [], "dimensions": [2, 2], "terminal": 1, "probability_true": [0.33], "probability_false": [0.67], "proficiency": 0.2380055493044546, "degreeCarefull": 0, "gender": "Female", "known": 0.2380055493044546, "learnt": 0, "age": 14, "classID": 1}, {"id": 229, "sequence": 6, "description": "Scale Factor", "children": [], "dimensions": [2, 2], "terminal": 1, "probability_true": [0.33], "probability_false": [0.67], "proficiency": 0.2477631806579867, "degreeCarefull": 0, "gender": "Female", "known": 0.2477631806579867, "learnt": 0, "age": 14, "classID": 1}, {"id": 230, "sequence": 10, "description": "Surface Area Cylinder", "children": [{"id": 23, "description": "Area Circle"}, {"id": 219, "description": "Nets of 3D Objects"}], "dimensions": [2, 2], "terminal": 0, "probability_true": [0.98, 0.98, 0.12, 0.12], "probability_false": [0.02, 0.02, 0.88, 0.88], "proficiency": 0.28739848076382934, "degreeCarefull": 1, "gender": "Female", "known": 0.28739848076382934, "learnt": 0, "age": 14, "classID": 1}, {"id": 231, "sequence": 9, "description": "Surface Area of Prism", "children": [{"id": 219, "description": "Nets of 3D Objects"}], "dimensions": [2], "terminal": 0, "probability_true": [0.98, 0.12], "probability_false": [0.02, 0.88], "proficiency": 0.20944366046740182, "degreeCarefull": 1, "gender": "Female", "known": 0.20944366046740182, "learnt": 0, "age": 14, "classID": 1}, {"id": 232, "sequence": 8, "description": "Surface Area Rectangular Prism", "children": [{"id": 225, "description": "Properties and Classification Rectangular Prisms"}, {"id": 219, "description": "Nets of 3D Objects"}], "dimensions": [2, 2], "terminal": 0, "probability_true": [0.98, 0.98, 0.12, 0.12], "probability_false": [0.02, 0.02, 0.88, 0.88], "proficiency": 0.2284050682341457, "degreeCarefull": 0, "gender": "Female", "known": 0.2284050682341457, "learnt": 0, "age": 14, "classID": 1}, {"id": 233, "sequence": 8, "description": "Surface Area Sphere", "children": [{"id": 219, "description": "Nets of 3D Objects"}], "dimensions": [2], "terminal": 0, "probability_true": [0.98, 0.12], "probability_false": [0.02, 0.88], "proficiency": 0.1482526813862873, "degreeCarefull": 0, "gender": "Female", "known": 0.1482526813862873, "learnt": 0, "age": 14, "classID": 1}, {"id": 234, "sequence": 10, "description": "Volume Cone", "children": [{"id": 213, "description": "Concept Volume"}], "dimensions": [2], "terminal": 0, "probability_true": [0.98, 0.12], "probability_false": [0.02, 0.88], "proficiency": 0.13973477589404626, "degreeCarefull": 0, "gender": "Female", "known": 0.13973477589404626, "learnt": 0, "age": 14, "classID": 1}, {"id": 235, "sequence": 10, "description": "Volume Cylinder", "children": [{"id": 213, "description": "Concept Volume"}], "dimensions": [2], "terminal": 0, "probability_true": [0.98, 0.12], "probability_false": [0.02, 0.88], "proficiency": 0.18780379060419639, "degreeCarefull": 1, "gender": "Female", "known": 0.18780379060419639, "learnt": 0, "age": 14, "classID": 1}, {"id": 236, "sequence": 10, "description": "Volume Pyramid", "children": [{"id": 28, "description": "Area Triangle"}, {"id": 213, "description": "Concept Volume"}], "dimensions": [2, 2], "terminal": 0, "probability_true": [0.98, 0.98, 0.12, 0.12], "probability_false": [0.02, 0.02, 0.88, 0.88], "proficiency": 0.12032165782631474, "degreeCarefull": 0, "gender": "Female", "known": 0.12032165782631474, "learnt": 0, "age": 14, "classID": 1}, {"id": 237, "sequence": 10, "description": "Volume Rectangular Prism", "children": [{"id": 26, "description": "Area Rectangle"}, {"id": 213, "description": "Concept Volume"}], "dimensions": [2, 2], "terminal": 0, "probability_true": [0.98, 0.98, 0.12, 0.12], "probability_false": [0.02, 0.02, 0.88, 0.88], "proficiency": 0.16004108725766578, "degreeCarefull": 0, "gender": "Female", "known": 0.16004108725766578, "learnt": 0, "age": 14, "classID": 1}, {"id": 30, "sequence": 15, "description": "Algebraic Solving", "children": [{"id": 31, "description": "Combining Like Terms"}, {"id": 315, "description": "Solving for a variable"}], "dimensions": [2, 2], "terminal": 0, "probability_true": [0.98, 0.98, 0.12, 0.12], "probability_false": [0.02, 0.02, 0.88, 0.88], "proficiency": 0.2234016409816077, "degreeCarefull": 0, "gender": "Female", "known": 0.2234016409816077, "learnt": 0, "age": 14, "classID": 1}, {"id": 31, "sequence": 11, "description": "Combining Like Terms", "children": [], "dimensions": [2, 2], "terminal": 1, "probability_true": [0.33], "probability_false": [0.67], "proficiency": 0.19008081447581948, "degreeCarefull": 1, "gender": "Female", "known": 0.19008081447581948, "learnt": 0, "age": 14, "classID": 1}, {"id": 32, "sequence": 16, "description": "Equation Solving More Than Two Steps", "children": [{"id": 30, "description": "Algebraic Solving"}], "dimensions": [2], "terminal": 0, "probability_true": [0.98, 0.12], "probability_false": [0.02, 0.88], "proficiency": 0.11962211065624863, "degreeCarefull": 0, "gender": "Female", "known": 0.11962211065624863, "learnt": 0, "age": 14, "classID": 1}, {"id": 33, "sequence": 16, "description": "Equation Solving Two or Fewer Steps", "children": [{"id": 30, "description": "Algebraic Solving"}], "dimensions": [2], "terminal": 0, "probability_true": [0.98, 0.12], "probability_false": [0.02, 0.88], "proficiency": 0.17795336573504117, "degreeCarefull": 1, "gender": "Female", "known": 0.17795336573504117, "learnt": 0, "age": 14, "classID": 1}, {"id": 34, "sequence": 11, "description": "Equivalent Fractions", "children": [], "dimensions": [2, 2], "terminal": 1, "probability_true": [0.33], "probability_false": [0.67], "proficiency": 0.23337672679758148, "degreeCarefull": 0, "gender": "Female", "known": 0.23337672679758148, "learnt": 0, "age": 14, "classID": 1}, {"id": 35, "sequence": 11, "description": "Exponents", "children": [], "dimensions": [2, 2], "terminal": 1, "probability_true": [0.33], "probability_false": [0.67], "proficiency": 0.1531385706847577, "degreeCarefull": 0, "gender": "Female", "known": 0.1531385706847577, "learnt": 0, "age": 14, "classID": 1}, {"id": 36, "sequence": 13, "description": "Factoring Polynomials Standard", "children": [{"id": 311, "description": "Polynomial Factors"}, {"id": 38, "description": "Parts of a Polyomial, Terms, Coefficient, Monomial, Exponent, Variable"}], "dimensions": [2, 2], "terminal": 0, "probability_true": [0.98, 0.98, 0.12, 0.12], "probability_false": [0.02, 0.02, 0.88, 0.88], "proficiency": 0.2514077295429362, "degreeCarefull": 1, "gender": "Female", "known": 0.2514077295429362, "learnt": 0, "age": 14, "classID": 1}, {"id": 37, "sequence": 12, "description": "Multiplying non Monomial Polynomials", "children": [{"id": 38, "description": "Parts of a Polyomial, Terms, Coefficient, Monomial, Exponent, Variable"}], "dimensions": [2], "terminal": 0, "probability_true": [0.98, 0.12], "probability_false": [0.02, 0.88], "proficiency": 0.2290569976047499, "degreeCarefull": 1, "gender": "Female", "known": 0.2290569976047499, "learnt": 0, "age": 14, "classID": 1}, {"id": 38, "sequence": 11, "description": "Parts of a Polyomial, Terms, Coefficient, Monomial, Exponent, Variable", "children": [], "dimensions": [2, 2], "terminal": 1, "probability_true": [0.33], "probability_false": [0.67], "proficiency": 0.21574769039275316, "degreeCarefull": 1, "gender": "Female", "known": 0.21574769039275316, "learnt": 0, "age": 14, "classID": 1}, {"id": 39, "sequence": 12, "description": "Picking Equation and Inequality from Choices", "children": [{"id": 317, "description": "Substitution"}], "dimensions": [2], "terminal": 0, "probability_true": [0.98, 0.12], "probability_false": [0.02, 0.88], "proficiency": 0.17053019549868928, "degreeCarefull": 0, "gender": "Female", "known": 0.17053019549868928, "learnt": 0, "age": 14, "classID": 1}, {"id": 310, "sequence": 11, "description": "Picking Expressions From Choices", "children": [{"id": 38, "description": "Parts of a Polyomial, Terms, Coefficient, Monomial, Exponent, Variable"}], "dimensions": [2], "terminal": 0, "probability_true": [0.98, 0.12], "probability_false": [0.02, 0.88], "proficiency": 0.21176411908661652, "degreeCarefull": 0, "gender": "Female", "known": 0.21176411908661652, "learnt": 0, "age": 14, "classID": 1}, {"id": 311, "sequence": 12, "description": "Polynomial Factors", "children": [{"id": 38, "description": "Parts of a Polyomial, Terms, Coefficient, Monomial, Exponent, Variable"}], "dimensions": [2], "terminal": 0, "probability_true": [0.98, 0.12], "probability_false": [0.02, 0.88], "proficiency": 0.2517433128786785, "degreeCarefull": 0, "gender": "Female", "known": 0.2517433128786785, "learnt": 0, "age": 14, "classID": 1}, {"id": 312, "sequence": 13, "description": "Quadratic Formula to Solve Quadratic Equation", "children": [{"id": 316, "description": "Square Root"}], "dimensions": [2], "terminal": 0, "probability_true": [0.98, 0.12], "probability_false": [0.02, 0.88], "proficiency": 0.19723370798266612, "degreeCarefull": 0, "gender": "Female", "known": 0.19723370798266612, "learnt": 0, "age": 14, "classID": 1}, {"id": 313, "sequence": 11, "description": "Recognize Linear Pattern", "children": [{"id": 318, "description": "Write Linear Equation from Ordered Pairs"}, {"id": 319, "description": "Write Linear Equation from Situation"}], "dimensions": [2, 2], "terminal": 0, "probability_true": [0.98, 0.98, 0.12, 0.12], "probability_false": [0.02, 0.02, 0.88, 0.88], "proficiency": 0.20846856342918738, "degreeCarefull": 0, "gender": "Female", "known": 0.20846856342918738, "learnt": 0, "age": 14, "classID": 1}, {"id": 314, "sequence": 12, "description": "Simplifying Expressions positive exponents", "children": [{"id": 35, "description": "Exponents"}], "dimensions": [2], "terminal": 0, "probability_true": [0.98, 0.12], "probability_false": [0.02, 0.88], "proficiency": 0.2203867554874781, "degreeCarefull": 1, "gender": "Female", "known": 0.2203867554874781, "learnt": 0, "age": 14, "classID": 1}, {"id": 315, "sequence": 14, "description": "Solving for a variable", "children": [{"id": 316, "description": "Square Root"}, {"id": 317, "description": "Substitution"}], "dimensions": [2, 2], "terminal": 0, "probability_true": [0.98, 0.98, 0.12, 0.12], "probability_false": [0.02, 0.02, 0.88, 0.88], "proficiency": 0.2411049738648283, "degreeCarefull": 1, "gender": "Female", "known": 0.2411049738648283, "learnt": 0, "age": 14, "classID": 1}, {"id": 316, "sequence": 12, "description": "Square Root", "children": [{"id": 35, "description": "Exponents"}], "dimensions": [2], "terminal": 0, "probability_true": [0.98, 0.12], "probability_false": [0.02, 0.88], "proficiency": 0.27421939858192546, "degreeCarefull": 0, "gender": "Female", "known": 0.27421939858192546, "learnt": 0, "age": 14, "classID": 1}, {"id": 317, "sequence": 11, "description": "Substitution", "children": [{"id": 34, "description": "Equivalent Fractions"}], "dimensions": [2], "terminal": 0, "probability_true": [0.98, 0.12], "probability_false": [0.02, 0.88], "proficiency": 0.15444190064408625, "degreeCarefull": 1, "gender": "Female", "known": 0.15444190064408625, "learnt": 0, "age": 14, "classID": 1}, {"id": 318, "sequence": 12, "description": "Write Linear Equation from Ordered Pairs", "children": [{"id": 319, "description": "Write Linear Equation from Situation"}], "dimensions": [2], "terminal": 0, "probability_true": [0.98, 0.12], "probability_false": [0.02, 0.88], "proficiency": 0.08099263022925693, "degreeCarefull": 0, "gender": "Female", "known": 0.08099263022925693, "learnt": 0, "age": 14, "classID": 1}, {"id": 319, "sequence": 11, "description": "Write Linear Equation from Situation", "children": [], "dimensions": [2, 2], "terminal": 1, "probability_true": [0.33], "probability_false": [0.67], "proficiency": 0.1343454679026788, "degreeCarefull": 1, "gender": "Female", "known": 0.1343454679026788, "learnt": 0, "age": 14, "classID": 1}, {"id": 40, "sequence": 17, "description": "Bar Graph", "children": [], "dimensions": [2, 2], "terminal": 1, "probability_true": [0.33], "probability_false": [0.67], "proficiency": 0.1675646178078684, "degreeCarefull": 0, "gender": "Female", "known": 0.1675646178078684, "learnt": 0, "age": 14, "classID": 1}, {"id": 41, "sequence": 18, "description": "Box and Whisker", "children": [{"id": 44, "description": "Median"}], "dimensions": [2], "terminal": 0, "probability_true": [0.98, 0.12], "probability_false": [0.02, 0.88], "proficiency": 0.15328920310818492, "degreeCarefull": 0, "gender": "Female", "known": 0.15328920310818492, "learnt": 0, "age": 14, "classID": 1}, {"id": 42, "sequence": 17, "description": "Distributive Property", "children": [], "dimensions": [2, 2], "terminal": 1, "probability_true": [0.33], "probability_false": [0.67], "proficiency": 0.14499674765914966, "degreeCarefull": 0, "gender": "Female", "known": 0.14499674765914966, "learnt": 0, "age": 14, "classID": 1}, {"id": 43, "sequence": 17, "description": "Histogram as Table or Graph", "children": [], "dimensions": [2, 2], "terminal": 1, "probability_true": [0.33], "probability_false": [0.67], "proficiency": 0.14913072672299826, "degreeCarefull": 0, "gender": "Female", "known": 0.14913072672299826, "learnt": 0, "age": 14, "classID": 1}, {"id": 44, "sequence": 17, "description": "Median", "children": [], "dimensions": [2, 2], "terminal": 1, "probability_true": [0.33], "probability_false": [0.67], "proficiency": 0.11646959438153537, "degreeCarefull": 0, "gender": "Female", "known": 0.11646959438153537, "learnt": 0, "age": 14, "classID": 1}, {"id": 45, "sequence": 19, "description": "Probability of a Single Event", "children": [{"id": 417, "description": "Probability definitions and properties"}], "dimensions": [2], "terminal": 0, "probability_true": [0.98, 0.12], "probability_false": [0.02, 0.88], "proficiency": 0.17460028781647624, "degreeCarefull": 0, "gender": "Female", "known": 0.17460028781647624, "learnt": 0, "age": 14, "classID": 1}, {"id": 46, "sequence": 21, "description": "Probability of Two Distinct Events", "children": [{"id": 45, "description": "Probability of a Single Event"}, {"id": 417, "description": "Probability definitions and properties"}], "dimensions": [2, 2], "terminal": 0, "probability_true": [0.98, 0.98, 0.12, 0.12], "probability_false": [0.02, 0.02, 0.88, 0.88], "proficiency": 0.1615478652788661, "degreeCarefull": 1, "gender": "Female", "known": 0.1615478652788661, "learnt": 0, "age": 14, "classID": 1}, {"id": 47, "sequence": 17, "description": "Tree Diagrams, Lists for Counting", "children": [], "dimensions": [2, 2], "terminal": 1, "probability_true": [0.33], "probability_false": [0.67], "proficiency": 0.20915622700550482, "degreeCarefull": 1, "gender": "Female", "known": 0.20915622700550482, "learnt": 0, "age": 14, "classID": 1}, {"id": 48, "sequence": 17, "description": "Venn Diagram", "children": [{"id": 410, "description": "Percent Of"}], "dimensions": [2], "terminal": 0, "probability_true": [0.98, 0.12], "probability_false": [0.02, 0.88], "proficiency": 0.23192254646148425, "degreeCarefull": 0, "gender": "Female", "known": 0.23192254646148425, "learnt": 0, "age": 14, "classID": 1}, {"id": 49, "sequence": 17, "description": "Mean", "children": [], "dimensions": [2, 2], "terminal": 1, "probability_true": [0.33], "probability_false": [0.67], "proficiency": 0.14478017790915962, "degreeCarefull": 0, "gender": "Female", "known": 0.14478017790915962, "learnt": 0, "age": 14, "classID": 1}, {"id": 410, "sequence": 17, "description": "Percent Of", "children": [], "dimensions": [2, 2], "terminal": 1, "probability_true": [0.33], "probability_false": [0.67], "proficiency": 0.22565355691371225, "degreeCarefull": 1, "gender": "Female", "known": 0.22565355691371225, "learnt": 0, "age": 14, "classID": 1}, {"id": 411, "sequence": 17, "description": "Mode", "children": [], "dimensions": [2, 2], "terminal": 1, "probability_true": [0.33], "probability_false": [0.67], "proficiency": 0.1830831572279293, "degreeCarefull": 1, "gender": "Female", "known": 0.1830831572279293, "learnt": 0, "age": 14, "classID": 1}, {"id": 412, "sequence": 18, "description": "Sample Mean", "children": [{"id": 49, "description": "Mean"}], "dimensions": [2], "terminal": 0, "probability_true": [0.98, 0.12], "probability_false": [0.02, 0.88], "proficiency": 0.12540724801032593, "degreeCarefull": 0, "gender": "Female", "known": 0.12540724801032593, "learnt": 0, "age": 14, "classID": 1}, {"id": 413, "sequence": 19, "description": "Sample Standard Deviation", "children": [{"id": 412, "description": "Sample Mean"}], "dimensions": [2], "terminal": 0, "probability_true": [0.98, 0.12], "probability_false": [0.02, 0.88], "proficiency": 0.07953511749606412, "degreeCarefull": 1, "gender": "Female", "known": 0.07953511749606412, "learnt": 0, "age": 14, "classID": 1}, {"id": 414, "sequence": 17, "description": "Probability Distributions", "children": [{"id": 49, "description": "Mean"}], "dimensions": [2], "terminal": 0, "probability_true": [0.98, 0.12], "probability_false": [0.02, 0.88], "proficiency": 0.11684249618489356, "degreeCarefull": 1, "gender": "Female", "known": 0.11684249618489356, "learnt": 0, "age": 14, "classID": 1}, {"id": 415, "sequence": 19, "description": "Hypothesis Testing", "children": [{"id": 417, "description": "Probability definitions and properties"}], "dimensions": [2], "terminal": 0, "probability_true": [0.98, 0.12], "probability_false": [0.02, 0.88], "proficiency": 0.15986522042388576, "degreeCarefull": 1, "gender": "Female", "known": 0.15986522042388576, "learnt": 0, "age": 14, "classID": 1}, {"id": 416, "sequence": 19, "description": "Combinatorics and basic set theory notation", "children": [{"id": 417, "description": "Probability definitions and properties"}], "dimensions": [2], "terminal": 0, "probability_true": [0.98, 0.12], "probability_false": [0.02, 0.88], "proficiency": 0.16271619934303694, "degreeCarefull": 1, "gender": "Female", "known": 0.16271619934303694, "learnt": 0, "age": 14, "classID": 1}, {"id": 417, "sequence": 18, "description": "Probability definitions and properties", "children": [], "dimensions": [2, 2], "terminal": 1, "probability_true": [0.33], "probability_false": [0.67], "proficiency": 0.19718828600746752, "degreeCarefull": 1, "gender": "Female", "known": 0.19718828600746752, "learnt": 0, "age": 14, "classID": 1}, {"id": 418, "sequence": 18, "description": "Random variables, expectation, variance", "children": [{"id": 417, "description": "Probability definitions and properties"}], "dimensions": [2], "terminal": 0, "probability_true": [0.98, 0.12], "probability_false": [0.02, 0.88], "proficiency": 0.1333580055064017, "degreeCarefull": 1, "gender": "Female", "known": 0.1333580055064017, "learnt": 0, "age": 14, "classID": 1}, {"id": 419, "sequence": 20, "description": "Confidence Intervals: definitions, duality with hypothesis tests", "children": [{"id": 415, "description": "Hypothesis Testing"}], "dimensions": [2], "terminal": 0, "probability_true": [0.98, 0.12], "probability_false": [0.02, 0.88], "proficiency": 0.15217793509216146, "degreeCarefull": 0, "gender": "Female", "known": 0.15217793509216146, "learnt": 0, "age": 14, "classID": 1}, {"id": 50, "sequence": 27, "description": "Choose an Equation from Given Information", "children": [{"id": 51, "description": "Comparing and Identifying Slope/Rate of Change"}, {"id": 55, "description": "Graph Shape"}], "dimensions": [2, 2], "terminal": 0, "probability_true": [0.98, 0.98, 0.12, 0.12], "probability_false": [0.02, 0.02, 0.88, 0.88], "proficiency": 0.18354685236748197, "degreeCarefull": 0, "gender": "Female", "known": 0.18354685236748197, "learnt": 0, "age": 14, "classID": 1}, {"id": 51, "sequence": 24, "description": "Comparing and Identifying Slope/Rate of Change", "children": [{"id": 53, "description": "Finding Slope From Equation"}, {"id": 511, "description": "Unit Rate"}], "dimensions": [2, 2], "terminal": 0, "probability_true": [0.98, 0.98, 0.12, 0.12], "probability_false": [0.02, 0.02, 0.88, 0.88], "proficiency": 0.1534111024489897, "degreeCarefull": 0, "gender": "Female", "known": 0.1534111024489897, "learnt": 0, "age": 14, "classID": 1}, {"id": 52, "sequence": 22, "description": "Composition of Function Adding", "children": [], "dimensions": [2, 2], "terminal": 1, "probability_true": [0.33], "probability_false": [0.67], "proficiency": 0.11055007292911753, "degreeCarefull": 0, "gender": "Female", "known": 0.11055007292911753, "learnt": 0, "age": 14, "classID": 1}, {"id": 53, "sequence": 22, "description": "Finding Slope From Equation", "children": [], "dimensions": [2, 2], "terminal": 1, "probability_true": [0.33], "probability_false": [0.67], "proficiency": 0.05466506503108433, "degreeCarefull": 0, "gender": "Female", "known": 0.05466506503108433, "learnt": 0, "age": 14, "classID": 1}, {"id": 54, "sequence": 24, "description": "Finding y-intercept from Linear Equation", "children": [{"id": 512, "description": "X-Y Graph Reading"}], "dimensions": [2], "terminal": 0, "probability_true": [0.98, 0.12], "probability_false": [0.02, 0.88], "proficiency": 0.18491980971874197, "degreeCarefull": 0, "gender": "Female", "known": 0.18491980971874197, "learnt": 0, "age": 14, "classID": 1}, {"id": 56, "sequence": 24, "description": "Interpreting Coordinate Graphs", "children": [], "dimensions": [2, 2], "terminal": 1, "probability_true": [0.33], "probability_false": [0.67], "proficiency": 0.0861471383707749, "degreeCarefull": 0, "gender": "Female", "known": 0.0861471383707749, "learnt": 0, "age": 14, "classID": 1}, {"id": 55, "sequence": 25, "description": "Graph Shape", "children": [{"id": 56, "description": "Interpreting Coordinate Graphs"}, {"id": 59, "description": "Range"}], "dimensions": [2, 2], "terminal": 0, "probability_true": [0.98, 0.98, 0.12, 0.12], "probability_false": [0.02, 0.02, 0.88, 0.88], "proficiency": 0.1095598258921822, "degreeCarefull": 0, "gender": "Female", "known": 0.1095598258921822, "learnt": 0, "age": 14, "classID": 1}, {"id": 58, "sequence": 23, "description": "Point Plotting", "children": [{"id": 56, "description": "Interpreting Coordinate Graphs"}], "dimensions": [2], "terminal": 0, "probability_true": [0.98, 0.12], "probability_false": [0.02, 0.88], "proficiency": 0.15299108597056768, "degreeCarefull": 0, "gender": "Female", "known": 0.15299108597056768, "learnt": 0, "age": 14, "classID": 1}, {"id": 57, "sequence": 22, "description": "Inverse Relations", "children": [], "dimensions": [2, 2], "terminal": 1, "probability_true": [0.33], "probability_false": [0.67], "proficiency": 0.1234756584421796, "degreeCarefull": 1, "gender": "Female", "known": 0.1234756584421796, "learnt": 0, "age": 14, "classID": 1}, {"id": 59, "sequence": 22, "description": "Range", "children": [], "dimensions": [2, 2], "terminal": 1, "probability_true": [0.33], "probability_false": [0.67], "proficiency": 0.07138650577276591, "degreeCarefull": 0, "gender": "Female", "known": 0.07138650577276591, "learnt": 0, "age": 14, "classID": 1}, {"id": 510, "sequence": 27, "description": "Solving Systems of Linear Equations by Graphing", "children": [{"id": 54, "description": "Finding y-intercept from Linear Equation"}, {"id": 55, "description": "Graph Shape"}], "dimensions": [2, 2], "terminal": 0, "probability_true": [0.98, 0.98, 0.12, 0.12], "probability_false": [0.02, 0.02, 0.88, 0.88], "proficiency": 0.1104652554281824, "degreeCarefull": 0, "gender": "Female", "known": 0.1104652554281824, "learnt": 0, "age": 14, "classID": 1}, {"id": 511, "sequence": 23, "description": "Unit Rate", "children": [{"id": 53, "description": "Finding Slope From Equation"}], "dimensions": [2], "terminal": 0, "probability_true": [0.98, 0.12], "probability_false": [0.02, 0.88], "proficiency": 0.12113187207900963, "degreeCarefull": 1, "gender": "Female", "known": 0.12113187207900963, "learnt": 0, "age": 14, "classID": 1}, {"id": 512, "sequence": 22, "description": "X-Y Graph Reading", "children": [], "dimensions": [2, 2], "terminal": 1, "probability_true": [0.33], "probability_false": [0.67], "proficiency": 0.17760756240555947, "degreeCarefull": 0, "gender": "Female", "known": 0.17760756240555947, "learnt": 0, "age": 14, "classID": 1}, {"id": 513, "sequence": 26, "description": "Write Linear Equation from Graph", "children": [{"id": 55, "description": "Graph Shape"}, {"id": 512, "description": "X-Y Graph Reading"}], "dimensions": [2, 2], "terminal": 0, "probability_true": [0.98, 0.98, 0.12, 0.12], "probability_false": [0.02, 0.02, 0.88, 0.88], "proficiency": 0.12824992904375995, "degreeCarefull": 0, "gender": "Female", "known": 0.12824992904375995, "learnt": 0, "age": 14, "classID": 1}, {"id": 514, "sequence": 26, "description": "Midpoints", "children": [{"id": 58, "description": "Point Plotting"}, {"id": 512, "description": "X-Y Graph Reading"}], "dimensions": [2, 2], "terminal": 0, "probability_true": [0.98, 0.98, 0.12, 0.12], "probability_false": [0.02, 0.02, 0.88, 0.88], "proficiency": 0.09951493225325467, "degreeCarefull": 1, "gender": "Female", "known": 0.09951493225325467, "learnt": 0, "age": 14, "classID": 1}]}